__init__.py
rutube.py
rutube_downloader-0.0.8.dist-info/METADATA
rutube_downloader-0.0.8.dist-info/WHEEL
rutube_downloader-0.0.8.dist-info/top_level.txt
rutube_downloader-0.0.8.dist-info/RECORD
