Metadata-Version: 2.1
Name: rutube-downloader
Version: 0.0.8
Summary: This is the simplest module for download videos from Rutube
Author-email: arch1_cs@mail.ru
Project-URL: Homepage, https://github.com/Valentin-Butorin/rutube_downloader
Project-URL: Repository, https://github.com/Valentin-Butorin/rutube_downloader.git
Classifier: Programming Language :: Python :: 3
Classifier: License :: OSI Approved :: MIT License
Classifier: Operating System :: OS Independent
Requires-Python: >=3.7
Requires-Dist: setuptools >=44.0.0
Requires-Dist: requests >=2.31.0
Requires-Dist: alive-progress >=3.1.4
Requires-Dist: m3u8 >=3.5.0
